{
  "kind": "singleType",
  "collectionName": "abouts",
  "info": {
    "singularName": "about",
    "pluralName": "abouts",
    "displayName": "About",
    "description": ""
  },
  "options": {
    "draftAndPublish": true
  },
  "pluginOptions": {},
  "attributes": {
    "CV": {
      "type": "media",
      "multiple": false,
      "required": false,
      "allowedTypes": [
        "images",
        "files",
        "videos",
        "audios"
      ]
    },
    "Awards": {
      "type": "dynamiczone",
      "components": [
        "about.about-title",
        "about.about-year",
        "about.about-item",
        "about.about-text"
      ]
    },
    "Bio": {
      "type": "dynamiczone",
      "components": [
        "about.about-item",
        "about.about-text",
        "about.about-title",
        "about.about-year"
      ]
    },
    "Residencies": {
      "type": "dynamiczone",
      "components": [
        "about.about-year",
        "about.about-title",
        "about.about-text",
        "about.about-item"
      ]
    },
    "Performances": {
      "type": "dynamiczone",
      "components": [
        "about.about-year",
        "about.about-title",
        "about.about-text",
        "about.about-item"
      ]
    },
    "Screenings": {
      "type": "dynamiczone",
      "components": [
        "about.about-year",
        "about.about-title",
        "about.about-text",
        "about.about-item"
      ]
    },
    "Talks": {
      "type": "dynamiczone",
      "components": [
        "about.about-year",
        "about.about-title",
        "about.about-text",
        "about.about-item"
      ]
    }
  }
}
